aws_assume_role_helper/__init__.py
aws_assume_role_helper/__main__.py
aws_assume_role_helper/commands.py
assume_mfa-0.4.0.dist-info/LICENSE
assume_mfa-0.4.0.dist-info/METADATA
assume_mfa-0.4.0.dist-info/WHEEL
assume_mfa-0.4.0.dist-info/entry_points.txt
assume_mfa-0.4.0.dist-info/top_level.txt
assume_mfa-0.4.0.dist-info/RECORD
