Metadata-Version: 2.1
Name: assume-mfa
Version: 0.4.0
Summary: Helper to easily assume IAM roles with MFA in AWS
Home-page: https://github.com/kunmingLiu/assume
Author: kunming0525
Author-email: kunming0525@gmail.com
License: MIT
Platform: UNKNOWN
Requires-Python: >3.5.2
Requires-Dist: pyyaml (~=4.2b1)
Requires-Dist: boto3 (~=1.5)
Provides-Extra: dev
Requires-Dist: flake8 ; extra == 'dev'
Requires-Dist: pylint ; extra == 'dev'
